backup_stage2/alu.sv
// ============================================================================
// File: rtl/core/alu.sv
// Description: Synthesizable 32-bit Arithmetic Logic Unit (ALU)
// ============================================================================

`timescale 1ns/1ps
import riscv_pkg::*;

module alu (
  input  alu_op_e     alu_op,
  input  logic [31:0] op_a,
  input  logic [31:0] op_b,
  output logic [31:0] alu_res,
  output logic        zero
);

  logic [4:0] shamt;
  assign shamt = op_b[4:0]; // Shift amount is lower 5 bits of operand B

  always_comb begin
    case (alu_op)
      ALU_ADD:  alu_res = op_a + op_b;
      ALU_SUB:  alu_res = op_a - op_b;
      ALU_SLL:  alu_res = op_a << shamt;
      ALU_SLT:  alu_res = ($signed(op_a) < $signed(op_b)) ? 32'd1 : 32'd0;
      ALU_SLTU: alu_res = (op_a < op_b) ? 32'd1 : 32'd0;
      ALU_XOR:  alu_res = op_a ^ op_b;
      ALU_SRL:  alu_res = op_a >> shamt;
      ALU_SRA:  alu_res = $signed(op_a) >>> shamt; // Arithmetic shift preserving sign
      ALU_OR:   alu_res = op_a | op_b;
      ALU_AND:  alu_res = op_a & op_b;
      ALU_PASS: alu_res = op_b;
      default:  alu_res = 32'h0;
    endcase
  end

  // Zero flag asserted when ALU result equals 0
  assign zero = (alu_res == 32'h0);

endmodule

tb/core/tb_alu.sv
// ============================================================================
// File: tb/core/tb_alu.sv
// Description: Comprehensive Self-Checking Testbench for 32-bit ALU
// ============================================================================

`timescale 1ns/1ps
import riscv_pkg::*;

module tb_alu;
  alu_op_e     alu_op;
  logic [31:0] op_a, op_b;
  logic [31:0] alu_res;
  logic        zero;

  int error_count = 0;

  alu dut (
    .alu_op(alu_op),
    .op_a(op_a),
    .op_b(op_b),
    .alu_res(alu_res),
    .zero(zero)
  );

  task check_alu(input string name, input logic [31:0] exp_res, input logic exp_zero);
    #1;
    if (alu_res !== exp_res || zero !== exp_zero) begin
      $display("[ERROR] %s: Expected (0x%08X, zero=%0b), Got (0x%08X, zero=%0b)", name, exp_res, exp_zero, alu_res, zero);
      error_count++;
    end else begin
      $display("[PASS] %s -> 0x%08X (zero=%0b)", name, alu_res, zero);
    end
  endtask

  initial begin
    $dumpfile("waves/tb_alu.vcd");
    $dumpvars(0, tb_alu);

    $display("=================================================");
    $display(" Starting 32-bit ALU Self-Checking Testbench     ");
    $display("=================================================");

    // ADD Test
    alu_op = ALU_ADD; op_a = 32'd25; op_b = 32'd75;
    check_alu("ADD (25 + 75)", 32'd100, 1'b0);

    // SUB Test (Result = 0 -> zero flag = 1)
    alu_op = ALU_SUB; op_a = 32'd50; op_b = 32'd50;
    check_alu("SUB (50 - 50 -> Zero)", 32'd0, 1'b1);

    // SLL Test (Logical Shift Left)
    alu_op = ALU_SLL; op_a = 32'h0000_0001; op_b = 32'd4;
    check_alu("SLL (1 << 4)", 32'h0000_0010, 1'b0);

    // SLT (Signed Less Than)
    alu_op = ALU_SLT; op_a = -32'd10; op_b = 32'd5;
    check_alu("SLT Signed (-10 < 5)", 32'd1, 1'b0);

    // SLTU (Unsigned Less Than)
    alu_op = ALU_SLTU; op_a = 32'hFFFF_FFFF; op_b = 32'd5; // 0xFFFFFFFF is large unsigned
    check_alu("SLTU Unsigned (0xFFFFFFFF < 5)", 32'd0, 1'b1);

    // SRA (Arithmetic Shift Right - preserves sign bit)
    alu_op = ALU_SRA; op_a = 32'hF000_0000; op_b = 32'd4;
    check_alu("SRA Signed Right Shift", 32'hFF00_0000, 1'b0);

    // SRL (Logical Shift Right - zero fills)
    alu_op = ALU_SRL; op_a = 32'hF000_0000; op_b = 32'd4;
    check_alu("SRL Logical Right Shift", 32'h0F00_0000, 1'b0);

    // Bitwise XOR, OR, AND
    alu_op = ALU_XOR; op_a = 32'hAAAA_5555; op_b = 32'hFFFF_FFFF;
    check_alu("XOR (~A)", 32'h5555_AAAA, 1'b0);

    alu_op = ALU_OR;  op_a = 32'hF0F0_0000; op_b = 32'h0F0F_0000;
    check_alu("OR", 32'hFFFF_0000, 1'b0);

    alu_op = ALU_AND; op_a = 32'hFFFF_0000; op_b = 32'h0FF0_0000;
    check_alu("AND", 32'h0FF0_0000, 1'b0);

    $display("=================================================");
    if (error_count == 0) begin
      $display(" ALL ALU TESTS PASSED (0 ERRORS)");
    end else begin
      $display(" ALU FAILED WITH %0d ERRORS", error_count);
    end
    $display("=================================================");
    $finish;
  end

endmodule

waves/tb_alu.vcd
$date
	Wed Sep 23 00:02:56 2026
$end
$version
	Icarus Verilog
$end
$timescale
	1ps
$end
$scope module tb_alu $end
$var wire 1 ! zero $end
$var wire 32 " alu_res [31:0] $end
$var reg 4 # alu_op [3:0] $end
$var reg 32 $ op_a [31:0] $end
$var reg 32 % op_b [31:0] $end
$var integer 32 & error_count [31:0] $end
$scope module dut $end
$var wire 4 ' alu_op [3:0] $end
$var wire 32 ( op_a [31:0] $end
$var wire 32 ) op_b [31:0] $end
$var wire 1 ! zero $end
$var wire 5 * shamt [4:0] $end
$var reg 32 + alu_res [31:0] $end
$upscope $end
$scope task check_alu $end
$var reg 32 , exp_res [31:0] $end
$var reg 1 - exp_zero $end
$upscope $end
$upscope $end
$enddefinitions $end
$comment Show the parameter values. $end
$dumpall
$end
#0
$dumpvars
0-
b1100100 ,
b1100100 +
b1011 *
b1001011 )
b11001 (
b0 '
b0 &
b1001011 %
b11001 $
b0 #
b1100100 "
0!
$end
#1000
b10010 *
1!
b0 "
b0 +
1-
b0 ,
b110010 %
b110010 )
b110010 $
b110010 (
b1 #
b1 '
#2000
b100 *
0!
b10000 "
b10000 +
0-
b10000 ,
b100 %
b100 )
b1 $
b1 (
b10 #
b10 '
#3000
b101 *
b1 "
b1 +
b1 ,
b101 %
b101 )
b11111111111111111111111111110110 $
b11111111111111111111111111110110 (
b11 #
b11 '
#4000
1!
b0 "
b0 +
1-
b0 ,
b11111111111111111111111111111111 $
b11111111111111111111111111111111 (
b100 #
b100 '
#5000
b100 *
0!
b11111111000000000000000000000000 "
b11111111000000000000000000000000 +
0-
b11111111000000000000000000000000 ,
b100 %
b100 )
b11110000000000000000000000000000 $
b11110000000000000000000000000000 (
b111 #
b111 '
#6000
b1111000000000000000000000000 "
b1111000000000000000000000000 +
b1111000000000000000000000000 ,
b110 #
b110 '
#7000
b11111 *
b1010101010101011010101010101010 "
b1010101010101011010101010101010 +
b1010101010101011010101010101010 ,
b11111111111111111111111111111111 %
b11111111111111111111111111111111 )
b10101010101010100101010101010101 $
b10101010101010100101010101010101 (
b101 #
b101 '
#8000
b0 *
b11111111111111110000000000000000 "
b11111111111111110000000000000000 +
b11111111111111110000000000000000 ,
b1111000011110000000000000000 %
b1111000011110000000000000000 )
b11110000111100000000000000000000 $
b11110000111100000000000000000000 (
b1000 #
b1000 '
#9000
b1111111100000000000000000000 "
b1111111100000000000000000000 +
b1111111100000000000000000000 ,
b1111111100000000000000000000 %
b1111111100000000000000000000 )
b11111111111111110000000000000000 $
b11111111111111110000000000000000 (
b1001 #
b1001 '
