rtl/core/register_file.sv
// ============================================================================
// File: rtl/core/register_file.sv
// Description: 32 x 32-bit Dual-Read, Single-Write Register File
// ============================================================================

`timescale 1ns/1ps

module register_file (
  input  logic        clk,
  input  logic        rst_n,

  // Read Port 1 (rs1)
  input  logic [4:0]  raddr1,
  output logic [31:0] rdata1,

  // Read Port 2 (rs2)
  input  logic [4:0]  raddr2,
  output logic [31:0] rdata2,

  // Write Port (rd)
  input  logic        we,
  input  logic [4:0]  waddr,
  input  logic [31:0] wdata
);

  // 32 General-Purpose Registers
  logic [31:0] regs [0:31];

  // Synchronous Write Operation with Active-Low Reset
  always_ff @(posedge clk or negedge rst_n) begin
    if (!rst_n) begin
      for (int i = 0; i < 32; i++) begin
        regs[i] <= 32'h0;
      end
    end else begin
      // Register x0 is read-only zero (writes to x0 are ignored)
      if (we && (waddr != 5'd0)) begin
        regs[waddr] <= wdata;
      end
    end
  end

  // Asynchronous Dual-Port Read with Write-Forwarding Bypass:
  // If reading the register currently being written, return new data immediately
  always_comb begin
    // Port 1
    if (raddr1 == 5'd0) begin
      rdata1 = 32'h0;
    end else if (we && (waddr == raddr1)) begin
      rdata1 = wdata; // Forwarding bypass
    end else begin
      rdata1 = regs[raddr1];
    end

    // Port 2
    if (raddr2 == 5'd0) begin
      rdata2 = 32'h0;
    end else if (we && (waddr == raddr2)) begin
      rdata2 = wdata; // Forwarding bypass
    end else begin
      rdata2 = regs[raddr2];
    end
  end

endmodule

tb/core/tb_register_file.sv
// ============================================================================
// File: tb/core/tb_register_file.sv
// Description: Comprehensive Self-Checking Testbench for Register File
// ============================================================================

`timescale 1ns/1ps

module tb_register_file;
  logic        clk;
  logic        rst_n;
  logic [4:0]  raddr1, raddr2, waddr;
  logic        we;
  logic [31:0] wdata;
  logic [31:0] rdata1, rdata2;

  int error_count = 0;

  // DUT Instantiation
  register_file dut (
    .clk(clk),
    .rst_n(rst_n),
    .raddr1(raddr1),
    .rdata1(rdata1),
    .raddr2(raddr2),
    .rdata2(rdata2),
    .we(we),
    .waddr(waddr),
    .wdata(wdata)
  );

  // Clock Generation (100MHz -> 10ns period)
  always #5 clk = ~clk;

  initial begin
    $dumpfile("waves/tb_register_file.vcd");
    $dumpvars(0, tb_register_file);

    clk   = 0;
    rst_n = 0;
    we    = 0;
    raddr1 = 0;
    raddr2 = 0;
    waddr  = 0;
    wdata  = 0;

    $display("=================================================");
    $display(" Starting Register File Self-Checking Testbench  ");
    $display("=================================================");

    // 1. Reset Test
    #15 rst_n = 1;

    // 2. Write to x0 (Must remain 0)
    @(posedge clk);
    we = 1; waddr = 5'd0; wdata = 32'hDEAD_BEEF;
    @(posedge clk);
    we = 0; raddr1 = 5'd0;
    #1;
    if (rdata1 !== 32'h0) begin
      $display("[ERROR] x0 is not 0! Read: 0x%08X", rdata1);
      error_count++;
    end else begin
      $display("[PASS] x0 zero-invariance check passed.");
    end

    // 3. Sequential Write and Read for Registers x1 to x31
    for (int i = 1; i < 32; i++) begin
      @(posedge clk);
      we = 1; waddr = i[4:0]; wdata = (i * 32'h1111_1111);
    end
    @(posedge clk);
    we = 0;

    // Check all written registers
    for (int i = 1; i < 32; i++) begin
      raddr1 = i[4:0];
      #1;
      if (rdata1 !== (i * 32'h1111_1111)) begin
        $display("[ERROR] Mismatch at x%0d: Expected 0x%08X, got 0x%08X", i, (i * 32'h1111_1111), rdata1);
        error_count++;
      end
    end

    // 4. Simultaneous Write & Read Bypass Forwarding
    @(posedge clk);
    we = 1; waddr = 5'd10; wdata = 32'hCAFE_BABE;
    raddr1 = 5'd10; // Reading same cycle
    #1;
    if (rdata1 !== 32'hCAFE_BABE) begin
      $display("[ERROR] Bypass forwarding failed! Got 0x%08X", rdata1);
      error_count++;
    end else begin
      $display("[PASS] Write-forwarding bypass check passed.");
    end

    @(posedge clk);
    we = 0;

    $display("=================================================");
    if (error_count == 0) begin
      $display(" ALL REGISTER FILE TESTS PASSED (0 ERRORS)");
    end else begin
      $display(" REGISTER FILE FAILED WITH %0d ERRORS", error_count);
    end
    $display("=================================================");
    $finish;
  end

endmodule

waves/tb_register_file.vcd
$date
	Tue Sep 22 23:56:51 2026
$end
$version
	Icarus Verilog
$end
$timescale
	1ps
$end
$scope module tb_register_file $end
$var wire 32 ! rdata2 [31:0] $end
$var wire 32 " rdata1 [31:0] $end
$var reg 1 # clk $end
$var reg 5 $ raddr1 [4:0] $end
$var reg 5 % raddr2 [4:0] $end
$var reg 1 & rst_n $end
$var reg 5 ' waddr [4:0] $end
$var reg 32 ( wdata [31:0] $end
$var reg 1 ) we $end
$var integer 32 * error_count [31:0] $end
$scope module dut $end
$var wire 1 # clk $end
$var wire 5 + raddr1 [4:0] $end
$var wire 5 , raddr2 [4:0] $end
$var wire 1 & rst_n $end
$var wire 5 - waddr [4:0] $end
$var wire 32 . wdata [31:0] $end
$var wire 1 ) we $end
$var reg 32 / rdata1 [31:0] $end
$var reg 32 0 rdata2 [31:0] $end
$scope begin $ivl_for_loop0 $end
$var integer 32 1 i [31:0] $end
$upscope $end
$upscope $end
$scope begin $ivl_for_loop1 $end
$var integer 32 2 i [31:0] $end
$upscope $end
$scope begin $ivl_for_loop2 $end
$var integer 32 3 i [31:0] $end
$upscope $end
$upscope $end
$enddefinitions $end
$comment Show the parameter values. $end
$dumpall
$end
#0
$dumpvars
b0 3
b0 2
b100000 1
b0 0
b0 /
b0 .
b0 -
b0 ,
b0 +
b0 *
0)
b0 (
b0 '
0&
b0 %
b0 $
0#
b0 "
b0 !
$end
#5000
b100000 1
1#
#10000
0#
#15000
b11011110101011011011111011101111 (
b11011110101011011011111011101111 .
1)
1#
1&
#20000
0#
#25000
0)
1#
#26000
b1 2
#30000
0#
#35000
b10 2
b10001000100010001000100010001 (
b10001000100010001000100010001 .
b1 '
b1 -
1)
1#
#40000
0#
#45000
b11 2
b100010001000100010001000100010 (
b100010001000100010001000100010 .
b10 '
b10 -
1#
#50000
0#
#55000
b100 2
b110011001100110011001100110011 (
b110011001100110011001100110011 .
b11 '
b11 -
1#
#60000
0#
#65000
b101 2
b1000100010001000100010001000100 (
b1000100010001000100010001000100 .
b100 '
b100 -
1#
#70000
0#
#75000
b110 2
b1010101010101010101010101010101 (
b1010101010101010101010101010101 .
b101 '
b101 -
1#
#80000
0#
#85000
b111 2
b1100110011001100110011001100110 (
b1100110011001100110011001100110 .
b110 '
b110 -
1#
#90000
0#
#95000
b1000 2
b1110111011101110111011101110111 (
b1110111011101110111011101110111 .
b111 '
b111 -
1#
#100000
0#
#105000
b1001 2
b10001000100010001000100010001000 (
b10001000100010001000100010001000 .
b1000 '
b1000 -
1#
#110000
0#
#115000
b1010 2
b10011001100110011001100110011001 (
b10011001100110011001100110011001 .
b1001 '
b1001 -
1#
#120000
0#
#125000
b1011 2
b10101010101010101010101010101010 (
b10101010101010101010101010101010 .
b1010 '
b1010 -
1#
#130000
0#
#135000
b1100 2
b10111011101110111011101110111011 (
b10111011101110111011101110111011 .
b1011 '
b1011 -
1#
#140000
0#
#145000
b1101 2
b11001100110011001100110011001100 (
b11001100110011001100110011001100 .
b1100 '
b1100 -
1#
#150000
0#
#155000
b1110 2
b11011101110111011101110111011101 (
b11011101110111011101110111011101 .
b1101 '
b1101 -
1#
#160000
0#
#165000
b1111 2
b11101110111011101110111011101110 (
b11101110111011101110111011101110 .
b1110 '
b1110 -
1#
#170000
0#
#175000
b10000 2
b11111111111111111111111111111111 (
b11111111111111111111111111111111 .
b1111 '
b1111 -
1#
#180000
0#
#185000
b10001 2
b10001000100010001000100010000 (
b10001000100010001000100010000 .
b10000 '
b10000 -
1#
#190000
0#
#195000
b10010 2
b100010001000100010001000100001 (
b100010001000100010001000100001 .
b10001 '
b10001 -
1#
#200000
0#
#205000
b10011 2
b110011001100110011001100110010 (
b110011001100110011001100110010 .
b10010 '
b10010 -
1#
#210000
0#
#215000
b10100 2
b1000100010001000100010001000011 (
b1000100010001000100010001000011 .
b10011 '
b10011 -
1#
#220000
0#
#225000
b10101 2
b1010101010101010101010101010100 (
b1010101010101010101010101010100 .
b10100 '
b10100 -
1#
#230000
0#
#235000
b10110 2
b1100110011001100110011001100101 (
b1100110011001100110011001100101 .
b10101 '
b10101 -
1#
#240000
0#
#245000
b10111 2
b1110111011101110111011101110110 (
b1110111011101110111011101110110 .
b10110 '
b10110 -
1#
#250000
0#
#255000
b11000 2
b10001000100010001000100010000111 (
b10001000100010001000100010000111 .
b10111 '
b10111 -
1#
#260000
0#
#265000
b11001 2
b10011001100110011001100110011000 (
b10011001100110011001100110011000 .
b11000 '
b11000 -
1#
#270000
0#
#275000
b11010 2
b10101010101010101010101010101001 (
b10101010101010101010101010101001 .
b11001 '
b11001 -
1#
#280000
0#
#285000
b11011 2
b10111011101110111011101110111010 (
b10111011101110111011101110111010 .
b11010 '
b11010 -
1#
#290000
0#
#295000
b11100 2
b11001100110011001100110011001011 (
b11001100110011001100110011001011 .
b11011 '
b11011 -
1#
#300000
0#
#305000
b11101 2
b11011101110111011101110111011100 (
b11011101110111011101110111011100 .
b11100 '
b11100 -
1#
#310000
0#
#315000
b11110 2
b11101110111011101110111011101101 (
b11101110111011101110111011101101 .
b11101 '
b11101 -
1#
#320000
0#
#325000
b11111 2
b11111111111111111111111111111110 (
b11111111111111111111111111111110 .
b11110 '
b11110 -
1#
#330000
0#
#335000
b100000 2
b10001000100010001000100001111 (
b10001000100010001000100001111 .
b11111 '
b11111 -
1#
#340000
0#
#345000
b10001000100010001000100010001 "
b10001000100010001000100010001 /
b1 $
b1 +
b1 3
0)
1#
#346000
b100010001000100010001000100010 "
b100010001000100010001000100010 /
b10 $
b10 +
b10 3
#347000
b110011001100110011001100110011 "
b110011001100110011001100110011 /
b11 $
b11 +
b11 3
#348000
b1000100010001000100010001000100 "
b1000100010001000100010001000100 /
b100 $
b100 +
b100 3
#349000
b1010101010101010101010101010101 "
b1010101010101010101010101010101 /
b101 $
b101 +
b101 3
#350000
b1100110011001100110011001100110 "
b1100110011001100110011001100110 /
b110 $
b110 +
b110 3
0#
#351000
b1110111011101110111011101110111 "
b1110111011101110111011101110111 /
b111 $
b111 +
b111 3
#352000
b10001000100010001000100010001000 "
b10001000100010001000100010001000 /
b1000 $
b1000 +
b1000 3
#353000
b10011001100110011001100110011001 "
b10011001100110011001100110011001 /
b1001 $
b1001 +
b1001 3
#354000
b10101010101010101010101010101010 "
b10101010101010101010101010101010 /
b1010 $
b1010 +
b1010 3
#355000
b10111011101110111011101110111011 "
b10111011101110111011101110111011 /
b1011 $
b1011 +
b1011 3
1#
#356000
b11001100110011001100110011001100 "
b11001100110011001100110011001100 /
b1100 $
b1100 +
b1100 3
#357000
b11011101110111011101110111011101 "
b11011101110111011101110111011101 /
b1101 $
b1101 +
b1101 3
#358000
b11101110111011101110111011101110 "
b11101110111011101110111011101110 /
b1110 $
b1110 +
b1110 3
#359000
b11111111111111111111111111111111 "
b11111111111111111111111111111111 /
b1111 $
b1111 +
b1111 3
#360000
b10001000100010001000100010000 "
b10001000100010001000100010000 /
b10000 $
b10000 +
b10000 3
0#
#361000
b100010001000100010001000100001 "
b100010001000100010001000100001 /
b10001 $
b10001 +
b10001 3
#362000
b110011001100110011001100110010 "
b110011001100110011001100110010 /
b10010 $
b10010 +
b10010 3
#363000
b1000100010001000100010001000011 "
b1000100010001000100010001000011 /
b10011 $
b10011 +
b10011 3
#364000
b1010101010101010101010101010100 "
b1010101010101010101010101010100 /
b10100 $
b10100 +
b10100 3
#365000
b1100110011001100110011001100101 "
b1100110011001100110011001100101 /
b10101 $
b10101 +
b10101 3
1#
#366000
b1110111011101110111011101110110 "
b1110111011101110111011101110110 /
b10110 $
b10110 +
b10110 3
#367000
b10001000100010001000100010000111 "
b10001000100010001000100010000111 /
b10111 $
b10111 +
b10111 3
#368000
b10011001100110011001100110011000 "
b10011001100110011001100110011000 /
b11000 $
b11000 +
b11000 3
#369000
b10101010101010101010101010101001 "
b10101010101010101010101010101001 /
b11001 $
b11001 +
b11001 3
#370000
b10111011101110111011101110111010 "
b10111011101110111011101110111010 /
b11010 $
b11010 +
b11010 3
0#
#371000
b11001100110011001100110011001011 "
b11001100110011001100110011001011 /
b11011 $
b11011 +
b11011 3
#372000
b11011101110111011101110111011100 "
b11011101110111011101110111011100 /
b11100 $
b11100 +
b11100 3
#373000
b11101110111011101110111011101101 "
b11101110111011101110111011101101 /
b11101 $
b11101 +
b11101 3
#374000
b11111111111111111111111111111110 "
b11111111111111111111111111111110 /
b11110 $
b11110 +
b11110 3
#375000
b10001000100010001000100001111 "
b10001000100010001000100001111 /
b11111 $
b11111 +
b11111 3
1#
#376000
b100000 3
#380000
0#
#385000
b11001010111111101011101010111110 "
b11001010111111101011101010111110 /
b1010 $
b1010 +
b11001010111111101011101010111110 (
b11001010111111101011101010111110 .
b1010 '
b1010 -
1)
1#
#390000
0#
#395000
0)
1#
